ipywidget_jsonschema_embed/__init__.py
ipywidget_jsonschema_embed/build/asset-manifest.json
ipywidget_jsonschema_embed/build/favicon.ico
ipywidget_jsonschema_embed/build/index.html
ipywidget_jsonschema_embed/build/logo192.png
ipywidget_jsonschema_embed/build/logo512.png
ipywidget_jsonschema_embed/build/manifest.json
ipywidget_jsonschema_embed/build/robots.txt
ipywidget_jsonschema_embed/build/static/css/main.4efb37a3.css
ipywidget_jsonschema_embed/build/static/js/27.19b9ab20.chunk.js
ipywidget_jsonschema_embed/build/static/js/main.f14e84cf.js
ipywidget_jsonschema_embed/build/static/js/main.f14e84cf.js.LICENSE.txt
ipywidget_jsonschema_embed-0.0.5.data/data/web/27.19b9ab20.chunk.js
ipywidget_jsonschema_embed-0.0.5.data/data/web/asset-manifest.json
ipywidget_jsonschema_embed-0.0.5.data/data/web/favicon.ico
ipywidget_jsonschema_embed-0.0.5.data/data/web/index.html
ipywidget_jsonschema_embed-0.0.5.data/data/web/logo192.png
ipywidget_jsonschema_embed-0.0.5.data/data/web/logo512.png
ipywidget_jsonschema_embed-0.0.5.data/data/web/main.4efb37a3.css
ipywidget_jsonschema_embed-0.0.5.data/data/web/main.f14e84cf.js
ipywidget_jsonschema_embed-0.0.5.data/data/web/main.f14e84cf.js.LICENSE.txt
ipywidget_jsonschema_embed-0.0.5.data/data/web/manifest.json
ipywidget_jsonschema_embed-0.0.5.data/data/web/robots.txt
ipywidget_jsonschema_embed-0.0.5.dist-info/METADATA
ipywidget_jsonschema_embed-0.0.5.dist-info/WHEEL
ipywidget_jsonschema_embed-0.0.5.dist-info/top_level.txt
ipywidget_jsonschema_embed-0.0.5.dist-info/RECORD
