Metadata-Version: 2.1
Name: ipywidget-jsonschema-embed
Version: 0.0.5
Summary: ipywidget_jsonschema_embed
Home-page: https://github.com/hp027/ipywidget-jsonschema-embed
Author: hp027
Author-email: hp027@foxmail.com
License: UNKNOWN
Platform: UNKNOWN
Classifier: Programming Language :: Python :: 3
Classifier: License :: OSI Approved :: MIT License
Classifier: Operating System :: OS Independent
Requires-Python: >=3.6
Requires-Dist: flask
Requires-Dist: jupyter-server-proxy
